<annotation>
	<folder>motor</folder>
	<filename>46b90de6-279f-438e-9bf7-78c254534f19.jpg</filename>
	<path>/Users/murilokakazu/Projects/turing/datasets/esp32_motor/training/motor/46b90de6-279f-438e-9bf7-78c254534f19.jpg</path>
	<source>
		<database>Unknown</database>
	</source>
	<size>
		<width>480</width>
		<height>320</height>
		<depth>3</depth>
	</size>
	<segmented>0</segmented>
	<object>
		<name>motor</name>
		<pose>Unspecified</pose>
		<truncated>0</truncated>
		<difficult>0</difficult>
		<bndbox>
			<xmin>161</xmin>
			<ymin>139</ymin>
			<xmax>277</xmax>
			<ymax>292</ymax>
		</bndbox>
	</object>
</annotation>
