<annotation>
	<folder>motor</folder>
	<filename>ffa2cf4d-0f81-4df7-9226-314f5f7045ef.jpg</filename>
	<path>/Users/murilokakazu/Projects/turing/datasets/esp32_motor/training/motor/ffa2cf4d-0f81-4df7-9226-314f5f7045ef.jpg</path>
	<source>
		<database>Unknown</database>
	</source>
	<size>
		<width>480</width>
		<height>320</height>
		<depth>3</depth>
	</size>
	<segmented>0</segmented>
	<object>
		<name>motor</name>
		<pose>Unspecified</pose>
		<truncated>0</truncated>
		<difficult>0</difficult>
		<bndbox>
			<xmin>151</xmin>
			<ymin>157</ymin>
			<xmax>258</xmax>
			<ymax>301</ymax>
		</bndbox>
	</object>
</annotation>
