<annotation>
	<folder>esp32</folder>
	<filename>3aafcff9-3e9b-43bb-9e0b-3c521045d67b.jpg</filename>
	<path>/Users/murilokakazu/Projects/turing/datasets/esp32_motor/training/esp32/3aafcff9-3e9b-43bb-9e0b-3c521045d67b.jpg</path>
	<source>
		<database>Unknown</database>
	</source>
	<size>
		<width>480</width>
		<height>320</height>
		<depth>3</depth>
	</size>
	<segmented>0</segmented>
	<object>
		<name>esp32</name>
		<pose>Unspecified</pose>
		<truncated>0</truncated>
		<difficult>0</difficult>
		<bndbox>
			<xmin>161</xmin>
			<ymin>149</ymin>
			<xmax>227</xmax>
			<ymax>264</ymax>
		</bndbox>
	</object>
</annotation>
