<annotation>
	<folder>esp32</folder>
	<filename>539f3bbf-4947-4799-b367-f5088eab2d60.jpg</filename>
	<path>/Users/murilokakazu/Projects/turing/datasets/esp32_motor/training/esp32/539f3bbf-4947-4799-b367-f5088eab2d60.jpg</path>
	<source>
		<database>Unknown</database>
	</source>
	<size>
		<width>480</width>
		<height>320</height>
		<depth>3</depth>
	</size>
	<segmented>0</segmented>
	<object>
		<name>esp32</name>
		<pose>Unspecified</pose>
		<truncated>0</truncated>
		<difficult>0</difficult>
		<bndbox>
			<xmin>179</xmin>
			<ymin>142</ymin>
			<xmax>255</xmax>
			<ymax>265</ymax>
		</bndbox>
	</object>
</annotation>
